latlon_bbox/__init__.py
latlon_bbox/bbox.py
latlon_bbox-0.1.1.dist-info/METADATA
latlon_bbox-0.1.1.dist-info/WHEEL
latlon_bbox-0.1.1.dist-info/entry_points.txt
latlon_bbox-0.1.1.dist-info/licenses/LICENSE
latlon_bbox-0.1.1.dist-info/RECORD
