Metadata-Version: 2.4
Name: latlon-bbox
Version: 0.1.1
Summary: Compute bounding boxes from (lat, lon, radius_km)
Project-URL: Homepage, https://github.com/dinesh-kanakaraj/latlon-bbox
Project-URL: Issues, https://github.com/dinesh-kanakaraj/latlon-bbox/issues
Author-email: dinesh-kanakaraj <dineshkanakaraj2000@gmail.com>
License: 
License-File: LICENSE
Classifier: License :: OSI Approved :: MIT License
Classifier: Operating System :: OS Independent
Classifier: Programming Language :: Python :: 3
Requires-Python: >=3.8
